CHANGES
INSTALL.md
LICENSE
MANIFEST.in
README.md
runtests.py
setup.py
ATpy.egg-info/PKG-INFO
ATpy.egg-info/SOURCES.txt
ATpy.egg-info/dependency_links.txt
ATpy.egg-info/top_level.txt
atpy/__init__.py
atpy/asciitables.py
atpy/basetable.py
atpy/decorator.py
atpy/decorators.py
atpy/exceptions.py
atpy/fitstable.py
atpy/hdf5table.py
atpy/helpers.py
atpy/htmltable.py
atpy/ipactable.py
atpy/irsa_service.py
atpy/latextable.py
atpy/masked.py
atpy/odict.py
atpy/rechelper.py
atpy/registry.py
atpy/sqlhelper.py
atpy/sqltable.py
atpy/structhelper.py
atpy/version.py
atpy/vo_conesearch.py
atpy/votable.py
atpy/tests/__init__.py
atpy/tests/test_io.py
docs/Makefile
docs/api_table.rst
docs/api_tableset.rst
docs/atpy_logo.png
docs/conf.py
docs/contents.rst
docs/data.rst
docs/developers.rst
docs/format_ascii.rst
docs/format_fits.rst
docs/format_hdf5.rst
docs/format_ipac.rst
docs/format_online.rst
docs/format_sql.rst
docs/format_vo.rst
docs/formats.rst
docs/index.rst
docs/installation.rst
docs/introduction.rst
docs/manipulating.rst
docs/masking.rst
docs/migration.rst
docs/rtd-pip-requirements
docs/table_sets.rst
docs/tables.rst
examples/2mass.tbl
examples/3000030_1_sed.fits.gz
examples/aj285677t3_votable.xml
examples/catalog_1.fits.gz