Metadata-Version: 1.1
Name: ATpy
Version: 0.9.7
Summary: Astronomical Tables in Python
Home-page: http://atpy.readthedocs.org/
Author: Thomas Robitaille and Eli Bressert
Author-email: thomas.robitaille@gmail.com, elibre@users.sourceforge.net
License: MIT
Keywords: Scientific/Engineering
Platform: UNKNOWN
Classifier: Development Status :: 4 - Beta
Classifier: Programming Language :: Python
Classifier: License :: OSI Approved :: MIT License
Requires: numpy
Requires: astropy
Provides: atpy
